MANIFEST.in
__info__.py
setup.py
./appomatic_autocomplete.egg-info/SOURCES.txt
./appomatic_autocomplete.egg-info/dependency_links.txt
./appomatic_autocomplete.egg-info/requires.txt
./appomatic_autocomplete.egg-info/top_level.txt
appomatic_autocomplete/__app__.py
appomatic_autocomplete/__init__.py
appomatic_autocomplete.egg-info/PKG-INFO
appomatic_autocomplete.egg-info/SOURCES.txt
appomatic_autocomplete.egg-info/dependency_links.txt
appomatic_autocomplete.egg-info/requires.txt
appomatic_autocomplete.egg-info/top_level.txt