Metadata-Version: 1.0
Name: appomatic-autocomplete
Version: 0.0.32
Summary: AutoComplete for ForeignKey and ManyToManyField.
Home-page: https://github.com/redhog/django-autocomplete
Author: RedHog (Egil Moeller)
Author-email: egil.moller@freecode.no
License: GPL
Keywords: appomatic autocomplete foreignkeys
Platform: UNKNOWN
